<?xml version="1.0"?>
<wpml-config>
  <custom-types>
     <custom-type translate="1">sln_service</custom-type>
     <custom-type translate="1">sln_attendant</custom-type>
     <custom-type translate="0">sln_booking</custom-type>
  </custom-types>
  <taxonomies>
   <taxonomy translate="1">sln_service_category</taxonomy>
  </taxonomies>
  <admin-texts>
    <key name="salon_settings">
      <key name="email_subject"/>
      <key name="disabled_message"/>
      <key name="gen_timetable"/>
      <key name="gen_address"/>
      <key name="email_nb_subject"/>
      <key name="new_booking_message"/>
      <key name="booking_update_message"/>
      <key name="feedback_message"/>
      <key name="last_step_note"/>
      <key name="checkout_fields">
      <key name="firstname"><key name="label"/></key><key name="lastname"><key name="label"/></key><key name="email"><key name="label"/></key><key name="phone"><key name="label"/></key><key name="address"><key name="label"/></key><key name="privacy"><key name="label"/></key><key name="qwe"><key name="label"/></key><key name="file"><key name="label"/></key><key name="test"><key name="label"/></key><key name="attachment"><key name="label"/></key><key name="custom_field_doctorsurgery"><key name="label"/></key><key name="custom_field_a"><key name="label"/></key><key name="custom_field_a1"><key name="label"/></key><key name="custom_field_a2"><key name="label"/></key><key name="custom_field_lifestyle"><key name="label"/></key><key name="custom_field_age_group"><key name="label"/></key><key name="custom_field_smoker"><key name="label"/></key><key name="covid_1"><key name="label"/></key><key name="covid_2"><key name="label"/></key><key name="covid_3"><key name="label"/></key><key name="covid_4"><key name="label"/></key><key name="covid_5"><key name="label"/></key><key name="covid_6"><key name="label"/></key><key name="covid_7"><key name="label"/></key><key name="covid_8"><key name="label"/></key><key name="covid_9"><key name="label"/></key><key name="covid_10"><key name="label"/></key><key name="covid_11"><key name="label"/></key><key name="covid_12"><key name="label"/></key><key name="covid_13"><key name="label"/></key><key name="covid_14"><key name="label"/></key><key name="covid_15"><key name="label"/></key><key name="covid_16"><key name="label"/></key><key name="covid_17"><key name="label"/></key><key name="covid_18"><key name="label"/></key><key name="covid_19"><key name="label"/></key><key name="covid_20"><key name="label"/></key><key name="covid_21"><key name="label"/></key><key name="covid_22"><key name="label"/></key><key name="please_note_if_you_are_exhibiting_any_covid_19_symptoms_or_have_been_asked_to_isolate_please_reschedule_your_session_via_my_bookings"><key name="label"/></key><key name="custom_field_c"><key name="label"/></key><key name="custom_field_d"><key name="label"/></key><key name="custom_field_e"><key name="label"/></key><key name="custom_field_f"><key name="label"/></key><key name="custom_field_g"><key name="label"/></key><key name="custom_field_h"><key name="label"/></key><key name="custom_field_i"><key name="label"/></key><key name="custom_field_l"><key name="label"/></key><key name="custom_field_la"><key name="label"/></key><key name="please_provide_details_to_any_yes_answers_above"><key name="label"/></key><key name="health_details_2"><key name="label"/></key><key name="health_1"><key name="label"/></key><key name="health_2"><key name="label"/></key><key name="health_3"><key name="label"/></key><key name="health_details_3"><key name="label"/></key><key name="health_4"><key name="label"/></key><key name="health_details_4"><key name="label"/></key><key name="health_5"><key name="label"/></key><key name="health_details_5"><key name="label"/></key><key name="health_7"><key name="label"/></key><key name="health_details_8"><key name="label"/></key><key name="health_11"><key name="label"/></key><key name="health_details_11"><key name="label"/></key><key name="health_14"><key name="label"/></key><key name="health_details_14"><key name="label"/></key><key name="health_20"><key name="label"/></key><key name="health_details_20"><key name="label"/></key><key name="health_20a"><key name="label"/></key><key name="health_details_20a"><key name="label"/></key><key name="health_21"><key name="label"/></key><key name="health_details_21"><key name="label"/></key><key name="health_21a"><key name="label"/></key><key name="health_details_21a"><key name="label"/></key><key name="health_23"><key name="label"/></key><key name="health_25"><key name="label"/></key><key name="health_details_25"><key name="label"/></key><key name="health_27"><key name="label"/></key><key name="health_details_23"><key name="label"/></key><key name="health_details_27"><key name="label"/></key><key name="options"><key name="label"/></key></key>
    </key>
  </admin-texts>
</wpml-config>
